{
	"name": "dataflow1",
	"properties": {
		"type": "MappingDataFlow",
		"typeProperties": {
			"sources": [
				{
					"dataset": {
						"referenceName": "SQL_Source_1",
						"type": "DatasetReference"
					},
					"name": "source1"
				}
			],
			"sinks": [
				{
					"dataset": {
						"referenceName": "SQL_Sink_Dataset",
						"type": "DatasetReference"
					},
					"name": "sqlsink1"
				}
			],
			"transformations": [],
			"scriptLines": [
				"source(output(",
				"          CustomerID as integer,",
				"          NameStyle as boolean,",
				"          Title as string,",
				"          FirstName as string,",
				"          MiddleName as string,",
				"          LastName as string,",
				"          Suffix as string,",
				"          CompanyName as string,",
				"          SalesPerson as string,",
				"          EmailAddress as string,",
				"          Phone as string,",
				"          PasswordHash as string,",
				"          PasswordSalt as string,",
				"          rowguid as string,",
				"          ModifiedDate as timestamp",
				"     ),",
				"     allowSchemaDrift: true,",
				"     validateSchema: false,",
				"     limit: 100,",
				"     enableCdc: true,",
				"     mode: 'read',",
				"     skipInitialLoad: false,",
				"     waterMarkColumn: 'CustomerID',",
				"     isolationLevel: 'READ_UNCOMMITTED',",
				"     format: 'table') ~> source1",
				"source1 sink(allowSchemaDrift: true,",
				"     validateSchema: false,",
				"     deletable:false,",
				"     insertable:true,",
				"     updateable:false,",
				"     upsertable:false,",
				"     format: 'table',",
				"     skipDuplicateMapInputs: true,",
				"     skipDuplicateMapOutputs: true,",
				"     errorHandlingOption: 'stopOnFirstError') ~> sqlsink1"
			]
		}
	}
}